thelogrus/__init__.py
thelogrus/cli.py
thelogrus/fileops.py
thelogrus/logging.py
thelogrus/time.py
thelogrus/utils.py
thelogrus/yaml.py
thelogrus-0.7.0.dist-info/entry_points.txt
thelogrus-0.7.0.dist-info/LICENSE
thelogrus-0.7.0.dist-info/WHEEL
thelogrus-0.7.0.dist-info/METADATA
thelogrus-0.7.0.dist-info/RECORD
