Metadata-Version: 2.1
Name: thelogrus
Version: 0.7.0
Summary: The Logrus is a collection of random utility functions
Home-page: https://github.com/unixorn/thelogrus
License: Apache 2.0
Author: Joe Block
Author-email: jpb@unixorn.net
Requires-Python: >=3.6,<4.0
Classifier: License :: Other/Proprietary License
Classifier: Programming Language :: Python :: 3
Classifier: Programming Language :: Python :: 3.10
Classifier: Programming Language :: Python :: 3.6
Classifier: Programming Language :: Python :: 3.7
Classifier: Programming Language :: Python :: 3.8
Classifier: Programming Language :: Python :: 3.9
Requires-Dist: dateutils (>=0.6.12,<0.7.0)
Requires-Dist: pyaml (>=21.10.1,<22.0.0)
Project-URL: Bug Tracker, https://github.com/unixorn/thelogrus/issues
Project-URL: Repository, https://github.com/unixorn/thelogrus
